atualizador/docs/index.md
atualizador/funcoes_mod/__init__.py
atualizador/funcoes_mod/Funcoes.py
atualizador/SRC-BOVESPA/B3_cotahist.py
atualizador/SRC-BOVESPA/B3_dados_h.py
atualizador/SRC-BOVESPA/B3_futuros.py
atualizador/SRC-BOVESPA/B3_milissegundo.py
atualizador/SRC-BOVESPA/B3_opcoes.py
atualizador/SRC-BOVESPA/B3_segundos.py
atualizador/SRC-BOVESPA/B3_ticker.py
atualizador/SRC-CORRELACAO/FL_AtivosCorrelacionados.py
atualizador/SRC-CRYPTO/BINANCE_ativos.py
atualizador/SRC-DERIBIT/FL_futurosBTC.py
atualizador/SRC-ESTUDOS/B3_ESTUDO.py
atualizador/SRC-TEDESCO/TD_acoes.py
atualizador/SRC-TEDESCO/TD_CryptoPerpetual.py
atualizador/SRC-TEDESCO/TD_Indices.py
atualizador/tests/Ajustes/REMOVER_DATE
atualizador/tests/Ajustes/ZIP_EXT.py
atualizador/tests/test_atualizador.py
atualizador-0.1.1.dist-info/WHEEL
atualizador-0.1.1.dist-info/METADATA
atualizador-0.1.1.dist-info/RECORD
