Metadata-Version: 2.1
Name: atualizador
Version: 0.1.1
Summary: Utilizado para atualizar dados de interesse da DIAX_LAB
Author: VitorKruel102
Author-email: vkruel.programador@gmail.com
Requires-Python: >=3.10,<4.0
Classifier: Programming Language :: Python :: 3
Classifier: Programming Language :: Python :: 3.10
Requires-Dist: numpy (>=1.22.4,<2.0.0)
Requires-Dist: pandas (>=1.4.2,<2.0.0)
